openaccess_epub-0.6.1.data/data/README.md
openaccess_epub-0.6.1.data/scripts/oaepub
openaccess_epub-0.6.1.dist-info/DESCRIPTION.rst
openaccess_epub-0.6.1.dist-info/METADATA
openaccess_epub-0.6.1.dist-info/top_level.txt
openaccess_epub-0.6.1.dist-info/WHEEL
openaccess_epub-0.6.1.dist-info/metadata.json
openaccess_epub-0.6.1.dist-info/RECORD
openaccess_epub/__init__.py
openaccess_epub/_version.py
openaccess_epub/publisher/frontiers.py
openaccess_epub/publisher/plos.py
openaccess_epub/publisher/__init__.py
openaccess_epub/commands/collection.py
openaccess_epub/commands/epubzip.py
openaccess_epub/commands/convert.py
openaccess_epub/commands/batch.py
openaccess_epub/commands/clearcache.py
openaccess_epub/commands/__init__.py
openaccess_epub/commands/validate.py
openaccess_epub/commands/configure.py
openaccess_epub/data/dtds/jpts21/modules.ent
openaccess_epub/data/dtds/jpts21/section.ent
openaccess_epub/data/dtds/jpts21/journalpubcustom-models.ent
openaccess_epub/data/dtds/jpts21/phrase.ent
openaccess_epub/data/dtds/jpts21/samplesmall-pub.xml
openaccess_epub/data/dtds/jpts21/default-classes.ent
openaccess_epub/data/dtds/jpts21/list.ent
openaccess_epub/data/dtds/jpts21/mathml2.dtd
openaccess_epub/data/dtds/jpts21/xmlspecchars.ent
openaccess_epub/data/dtds/jpts21/JournalPubReadme.txt
openaccess_epub/data/dtds/jpts21/oasis-exchange.ent
openaccess_epub/data/dtds/jpts21/mathml2-qname-1.mod
openaccess_epub/data/dtds/jpts21/XHTMLtablesetup.ent
openaccess_epub/data/dtds/jpts21/articlemeta.ent
openaccess_epub/data/dtds/jpts21/catalog.ent
openaccess_epub/data/dtds/jpts21/oasis-tablesetup.ent
openaccess_epub/data/dtds/jpts21/journalpubcustom-mixes.ent
openaccess_epub/data/dtds/jpts21/references.ent
openaccess_epub/data/dtds/jpts21/journalpublishing.dtd
openaccess_epub/data/dtds/jpts21/nlmcitation.ent
openaccess_epub/data/dtds/jpts21/catalog-v2.xml
openaccess_epub/data/dtds/jpts21/htmltable.dtd
openaccess_epub/data/dtds/jpts21/math.ent
openaccess_epub/data/dtds/jpts21/link.ent
openaccess_epub/data/dtds/jpts21/para.ent
openaccess_epub/data/dtds/jpts21/mathmlsetup.ent
openaccess_epub/data/dtds/jpts21/common.ent
openaccess_epub/data/dtds/jpts21/default-mixes.ent
