Metadata-Version: 2.0
Name: openaccess-epub
Version: 0.6.1
Summary: Converts OpenAccess Journal articles to EPUB
Home-page: https://github.com/SavinaRoja/openaccess_epub
Author: Paul Barton
Author-email: pablo.barton@gmail.com
License: UNKNOWN
Platform: UNKNOWN
Classifier: Development Status :: 3 - Alpha
Classifier: Environment :: Console
Classifier: Intended Audience :: Science/Research
Classifier: Intended Audience :: Developers
Classifier: Intended Audience :: Other Audience
Classifier: License :: OSI Approved :: GNU General Public License v3 or later (GPLv3+)
Classifier: Programming Language :: Python :: 3
Classifier: Operating System :: OS Independent
Classifier: Topic :: Text Processing :: Markup :: XML
Classifier: Topic :: Other/Nonlisted Topic
Requires-Dist: docopt
Requires-Dist: lxml
